Metadata-Version: 2.1
Name: gamefun
Version: 0.0.3
Summary: Game package
Home-page: UNKNOWN
Author: Lei Cui
Author-email: cuilei798@qq.com
Maintainer: Lei Cui
Maintainer-email: cuilei798@qq.com
License: MIT License
Platform: linux
Classifier: Operating System :: OS Independent
Classifier: License :: OSI Approved :: MIT License
Classifier: Programming Language :: Python :: 3
Requires-Python: >=3
